{
    "menu":[
        {
            "name":"Home",
            "url":"#"
        },
        {
            "name":"About",
            "url":"#about"
        },
        {
            "name":"Contact",
            "url":"#contact"
        }
    ],
    "carousel":[
        {
            "img":"https://gratisography.com/wp-content/uploads/2019/11/gratisography-landscape-laptop-1170x780.jpg",
            "url":"https://gratisography.com/photo/laptop-computer/"
        },
        {
            "img":"https://gratisography.com/wp-content/uploads/2018/05/gratisography-231H-1170x780.jpg",
            "url":"https://gratisography.com/photo/good-advice/"
        },
        {
            "img":"https://gratisography.com/wp-content/uploads/2018/05/gratisography-370H-1170x780.jpg",
            "url":"https://gratisography.com/photo/bunny-reading-newspaper/"
        }
    ]
}
